batchcmd/__init__.py
batchcmd/__main__.py
batchcmd/base.py
batchcmd/cli.py
batchcmd-0.0.2.dist-info/LICENSE
batchcmd-0.0.2.dist-info/METADATA
batchcmd-0.0.2.dist-info/WHEEL
batchcmd-0.0.2.dist-info/entry_points.txt
batchcmd-0.0.2.dist-info/top_level.txt
batchcmd-0.0.2.dist-info/RECORD
